{
  "categoryGroups": [
    { "id": "about_ourselves", "name_en": "About ourselves", "name_vi": "Về bản thân" },
    { "id": "by_pos", "name_en": "By parts of speech", "name_vi": "Theo từ loại" },
    { "id": "culture", "name_en": "Culture", "name_vi": "Văn hóa" },
    { "id": "lexicon", "name_en": "Lexicon", "name_vi": "Từ vựng" },
    { "id": "world_around", "name_en": "The world around us", "name_vi": "Thế giới xung quanh" },
    { "id": "by_level", "name_en": "By level", "name_vi": "Theo trình độ" },
    { "id": "by_test", "name_en": "By test", "name_vi": "Theo bài thi" },
    { "id": "by_origin", "name_en": "By origin", "name_vi": "Theo nguồn gốc" },
    { "id": "languages", "name_en": "Languages", "name_vi": "Ngôn ngữ" }
  ],
  "categories": [
    { "id": "emotions", "groupId": "about_ourselves", "name_en": "Emotions", "name_vi": "Cảm xúc", "icon": "face.smiling", "color": "#E57373" },
    { "id": "human_body", "groupId": "about_ourselves", "name_en": "Human body", "name_vi": "Cơ thể người", "icon": "figure.stand", "color": "#81C784" },
    { "id": "people", "groupId": "about_ourselves", "name_en": "People", "name_vi": "Con người", "icon": "person.3.fill", "color": "#64B5F6" },
    { "id": "sexology", "groupId": "about_ourselves", "name_en": "Sexology", "name_vi": "Tình dục học", "icon": "heart.circle", "color": "#F48FB1" },

    { "id": "verbs", "groupId": "by_pos", "name_en": "Verbs", "name_vi": "Động từ", "icon": "v.circle", "color": "#7986CB" },
    { "id": "nouns", "groupId": "by_pos", "name_en": "Nouns", "name_vi": "Danh từ", "icon": "n.circle", "color": "#4DB6AC" },
    { "id": "adjectives", "groupId": "by_pos", "name_en": "Adjectives", "name_vi": "Tính từ", "icon": "a.circle", "color": "#FFB74D" },

    { "id": "society", "groupId": "culture", "name_en": "Society", "name_vi": "Xã hội", "icon": "building.2", "color": "#90A4AE" },
    { "id": "literature", "groupId": "culture", "name_en": "Literature", "name_vi": "Văn học", "icon": "book.fill", "color": "#A1887F" },
    { "id": "talking", "groupId": "culture", "name_en": "Talking", "name_vi": "Giao tiếp", "icon": "bubble.left.and.bubble.right.fill", "color": "#9575CD" },
    { "id": "world_cuisine", "groupId": "culture", "name_en": "World cuisine", "name_vi": "Ẩm thực thế giới", "icon": "fork.knife", "color": "#FF8A65" },
    { "id": "art", "groupId": "culture", "name_en": "Art", "name_vi": "Nghệ thuật", "icon": "paintpalette.fill", "color": "#F06292" },
    { "id": "history", "groupId": "culture", "name_en": "History", "name_vi": "Lịch sử", "icon": "building.columns.fill", "color": "#8D6E63" },
    { "id": "music", "groupId": "culture", "name_en": "Music", "name_vi": "Âm nhạc", "icon": "music.note", "color": "#BA68C8" },
    { "id": "food", "groupId": "culture", "name_en": "Food", "name_vi": "Thức ăn", "icon": "carrot.fill", "color": "#FFB74D" },

    { "id": "beautiful_words", "groupId": "lexicon", "name_en": "Beautiful words", "name_vi": "Từ đẹp", "icon": "sparkles", "color": "#CE93D8" },
    { "id": "curse_words", "groupId": "lexicon", "name_en": "Curse words", "name_vi": "Từ chửi thề", "icon": "exclamationmark.bubble.fill", "color": "#EF5350" },
    { "id": "slang", "groupId": "lexicon", "name_en": "Slang", "name_vi": "Tiếng lóng", "icon": "quote.bubble.fill", "color": "#4DD0E1" },
    { "id": "expressions", "groupId": "lexicon", "name_en": "Expressions", "name_vi": "Thành ngữ", "icon": "text.quote", "color": "#AED581" },
    { "id": "funny_words", "groupId": "lexicon", "name_en": "Funny words", "name_vi": "Từ vui nhộn", "icon": "face.smiling.inverse", "color": "#FFD54F" },
    { "id": "legal_terms", "groupId": "lexicon", "name_en": "Legal terms", "name_vi": "Thuật ngữ pháp lý", "icon": "doc.text.fill", "color": "#78909C" },
    { "id": "office_language", "groupId": "lexicon", "name_en": "Office language", "name_vi": "Ngôn ngữ văn phòng", "icon": "desktopcomputer", "color": "#64B5F6" },
    { "id": "medicine", "groupId": "lexicon", "name_en": "Medicine", "name_vi": "Y học", "icon": "cross.case.fill", "color": "#E57373" },

    { "id": "business", "groupId": "world_around", "name_en": "Business", "name_vi": "Kinh doanh", "icon": "briefcase.fill", "color": "#4DB6AC" },
    { "id": "flora_fauna", "groupId": "world_around", "name_en": "Flora and fauna", "name_vi": "Động thực vật", "icon": "leaf.fill", "color": "#81C784" },
    { "id": "travel", "groupId": "world_around", "name_en": "Travel", "name_vi": "Du lịch", "icon": "airplane", "color": "#4FC3F7" },
    { "id": "science", "groupId": "world_around", "name_en": "Science", "name_vi": "Khoa học", "icon": "atom", "color": "#7986CB" },
    { "id": "technology", "groupId": "world_around", "name_en": "Technology", "name_vi": "Công nghệ", "icon": "laptopcomputer", "color": "#90A4AE" },
    { "id": "environment", "groupId": "world_around", "name_en": "Environment", "name_vi": "Môi trường", "icon": "globe.americas.fill", "color": "#66BB6A" },

    { "id": "beginner", "groupId": "by_level", "name_en": "Beginner", "name_vi": "Sơ cấp", "icon": "1.circle.fill", "color": "#81C784" },
    { "id": "intermediate", "groupId": "by_level", "name_en": "Intermediate", "name_vi": "Trung cấp", "icon": "2.circle.fill", "color": "#FFB74D" },
    { "id": "advanced", "groupId": "by_level", "name_en": "Advanced", "name_vi": "Cao cấp", "icon": "3.circle.fill", "color": "#E57373" },

    { "id": "gre", "groupId": "by_test", "name_en": "GRE", "name_vi": "GRE", "icon": "doc.text.magnifyingglass", "color": "#7986CB" },
    { "id": "sat", "groupId": "by_test", "name_en": "SAT", "name_vi": "SAT", "icon": "pencil.and.list.clipboard", "color": "#4DB6AC" },
    { "id": "spelling", "groupId": "by_test", "name_en": "Spelling", "name_vi": "Chính tả", "icon": "textformat.abc", "color": "#FFB74D" },

    { "id": "french_root", "groupId": "by_origin", "name_en": "French root", "name_vi": "Gốc Pháp", "icon": "flag.fill", "color": "#64B5F6" },
    { "id": "latin_root", "groupId": "by_origin", "name_en": "Latin root", "name_vi": "Gốc Latin", "icon": "building.columns", "color": "#A1887F" },
    { "id": "germanic_root", "groupId": "by_origin", "name_en": "Germanic root", "name_vi": "Gốc German", "icon": "flag.2.crossed.fill", "color": "#90A4AE" },
    { "id": "greek_root", "groupId": "by_origin", "name_en": "Greek root", "name_vi": "Gốc Hy Lạp", "icon": "theatermasks.fill", "color": "#CE93D8" },

    { "id": "spanish_words", "groupId": "languages", "name_en": "Spanish words", "name_vi": "Từ tiếng Tây Ban Nha", "icon": "character.bubble.fill", "color": "#FF8A65" },
    { "id": "french_words", "groupId": "languages", "name_en": "French words", "name_vi": "Từ tiếng Pháp", "icon": "character.bubble", "color": "#64B5F6" },
    { "id": "german_words", "groupId": "languages", "name_en": "German words", "name_vi": "Từ tiếng Đức", "icon": "character.bubble.ar", "color": "#90A4AE" }
  ],
  "words": [
    {
      "id": "w1",
      "term": "serendipity",
      "phonetic": "/ˌserənˈdɪpɪti/",
      "pos": "noun",
      "definition_en": "The occurrence of events by chance in a happy way",
      "meaning_vi": "Sự may mắn tình cờ, niềm vui bất ngờ",
      "examples": [
        { "en": "Finding that book was pure serendipity.", "vi": "Tìm được cuốn sách đó thật là may mắn." },
        { "en": "Their meeting was a beautiful serendipity.", "vi": "Cuộc gặp gỡ của họ là một sự tình cờ tuyệt đẹp." }
      ],
      "synonyms": ["luck", "fortune", "chance", "fate"],
      "origin": "Coined by Horace Walpole in 1754",
      "categoryId": "beautiful_words",
      "level": "advanced"
    },
    {
      "id": "w2",
      "term": "euphoria",
      "phonetic": "/juːˈfɔːriə/",
      "pos": "noun",
      "definition_en": "A feeling of intense excitement and happiness",
      "meaning_vi": "Cảm giác hưng phấn, vui sướng tột độ",
      "examples": [
        { "en": "She felt a sense of euphoria after winning.", "vi": "Cô ấy cảm thấy hưng phấn sau khi chiến thắng." },
        { "en": "The euphoria of the moment was unforgettable.", "vi": "Niềm vui sướng của khoảnh khắc đó thật khó quên." }
      ],
      "synonyms": ["elation", "joy", "ecstasy", "bliss"],
      "origin": "From Greek 'euphoros' meaning healthy",
      "categoryId": "emotions",
      "level": "intermediate"
    },
    {
      "id": "w3",
      "term": "melancholy",
      "phonetic": "/ˈmelənˌkɒli/",
      "pos": "noun",
      "definition_en": "A deep sadness or depression",
      "meaning_vi": "Nỗi buồn sâu lắng, u sầu",
      "examples": [
        { "en": "A sense of melancholy filled the room.", "vi": "Một cảm giác u sầu tràn ngập căn phòng." },
        { "en": "The music had a beautiful melancholy.", "vi": "Bản nhạc có một nỗi buồn đẹp đẽ." }
      ],
      "synonyms": ["sadness", "sorrow", "gloom", "wistfulness"],
      "origin": "From Greek 'melancholia'",
      "categoryId": "emotions",
      "level": "intermediate"
    },
    {
      "id": "w4",
      "term": "nostalgia",
      "phonetic": "/nɒˈstældʒə/",
      "pos": "noun",
      "definition_en": "A sentimental longing for the past",
      "meaning_vi": "Nỗi nhớ về quá khứ, hoài niệm",
      "examples": [
        { "en": "The old photos filled her with nostalgia.", "vi": "Những tấm ảnh cũ khiến cô ấy tràn ngập hoài niệm." },
        { "en": "He felt nostalgia for his childhood home.", "vi": "Anh ấy nhớ da diết ngôi nhà thời thơ ấu." }
      ],
      "synonyms": ["longing", "yearning", "reminiscence", "homesickness"],
      "origin": "From Greek 'nostos' (return home) + 'algos' (pain)",
      "categoryId": "emotions",
      "level": "intermediate"
    },
    {
      "id": "w5",
      "term": "gratitude",
      "phonetic": "/ˈɡrætɪtjuːd/",
      "pos": "noun",
      "definition_en": "The quality of being thankful",
      "meaning_vi": "Lòng biết ơn, sự cảm kích",
      "examples": [
        { "en": "She expressed her gratitude with a gift.", "vi": "Cô ấy thể hiện lòng biết ơn bằng một món quà." },
        { "en": "I have deep gratitude for your help.", "vi": "Tôi vô cùng biết ơn sự giúp đỡ của bạn." }
      ],
      "synonyms": ["thankfulness", "appreciation", "recognition"],
      "origin": "From Latin 'gratitudo'",
      "categoryId": "emotions",
      "level": "beginner"
    },
    {
      "id": "w6",
      "term": "anxious",
      "phonetic": "/ˈæŋkʃəs/",
      "pos": "adj",
      "definition_en": "Feeling worried or nervous",
      "meaning_vi": "Lo lắng, bồn chồn",
      "examples": [
        { "en": "She felt anxious before the interview.", "vi": "Cô ấy cảm thấy lo lắng trước buổi phỏng vấn." },
        { "en": "Don't be anxious, everything will be fine.", "vi": "Đừng lo lắng, mọi thứ sẽ ổn thôi." }
      ],
      "synonyms": ["worried", "nervous", "uneasy", "concerned"],
      "categoryId": "emotions",
      "level": "beginner"
    },
    {
      "id": "w7",
      "term": "resilient",
      "phonetic": "/rɪˈzɪliənt/",
      "pos": "adj",
      "definition_en": "Able to recover quickly from difficulties",
      "meaning_vi": "Kiên cường, có khả năng phục hồi",
      "examples": [
        { "en": "Children are remarkably resilient.", "vi": "Trẻ em có khả năng phục hồi đáng kinh ngạc." },
        { "en": "She proved to be resilient in tough times.", "vi": "Cô ấy chứng tỏ sự kiên cường trong thời kỳ khó khăn." }
      ],
      "synonyms": ["tough", "strong", "adaptable", "flexible"],
      "categoryId": "adjectives",
      "level": "intermediate"
    },
    {
      "id": "w8",
      "term": "empathy",
      "phonetic": "/ˈempəθi/",
      "pos": "noun",
      "definition_en": "The ability to understand others' feelings",
      "meaning_vi": "Sự đồng cảm, thấu hiểu",
      "examples": [
        { "en": "She showed great empathy for the victims.", "vi": "Cô ấy thể hiện sự đồng cảm lớn với các nạn nhân." },
        { "en": "Empathy is essential in relationships.", "vi": "Sự đồng cảm là thiết yếu trong các mối quan hệ." }
      ],
      "synonyms": ["compassion", "understanding", "sympathy"],
      "categoryId": "emotions",
      "level": "intermediate"
    },
    {
      "id": "w9",
      "term": "collaborate",
      "phonetic": "/kəˈlæbəreɪt/",
      "pos": "verb",
      "definition_en": "To work together on a project",
      "meaning_vi": "Hợp tác, cộng tác",
      "examples": [
        { "en": "We collaborate with other teams.", "vi": "Chúng tôi hợp tác với các nhóm khác." },
        { "en": "They collaborated on the research.", "vi": "Họ cộng tác trong nghiên cứu." }
      ],
      "synonyms": ["cooperate", "partner", "team up"],
      "categoryId": "office_language",
      "level": "intermediate"
    },
    {
      "id": "w10",
      "term": "deadline",
      "phonetic": "/ˈdedlaɪn/",
      "pos": "noun",
      "definition_en": "The latest time by which something must be done",
      "meaning_vi": "Hạn chót, thời hạn",
      "examples": [
        { "en": "The deadline is next Friday.", "vi": "Hạn chót là thứ Sáu tuần sau." },
        { "en": "We must meet the deadline.", "vi": "Chúng ta phải hoàn thành đúng hạn." }
      ],
      "synonyms": ["due date", "time limit", "cutoff"],
      "categoryId": "office_language",
      "level": "beginner"
    },
    {
      "id": "w11",
      "term": "community",
      "phonetic": "/kəˈmjuːnɪti/",
      "pos": "noun",
      "definition_en": "A group of people living in the same area",
      "meaning_vi": "Cộng đồng",
      "examples": [
        { "en": "The community came together to help.", "vi": "Cộng đồng đã cùng nhau giúp đỡ." },
        { "en": "She's active in the local community.", "vi": "Cô ấy hoạt động tích cực trong cộng đồng địa phương." }
      ],
      "synonyms": ["society", "neighborhood", "population"],
      "categoryId": "society",
      "level": "beginner"
    },
    {
      "id": "w12",
      "term": "diversity",
      "phonetic": "/daɪˈvɜːrsɪti/",
      "pos": "noun",
      "definition_en": "A range of different types or varieties",
      "meaning_vi": "Sự đa dạng",
      "examples": [
        { "en": "We celebrate diversity in our company.", "vi": "Chúng tôi tôn vinh sự đa dạng trong công ty." },
        { "en": "Diversity strengthens communities.", "vi": "Sự đa dạng làm mạnh cộng đồng." }
      ],
      "synonyms": ["variety", "difference", "range"],
      "categoryId": "society",
      "level": "intermediate"
    },
    {
      "id": "w13",
      "term": "ubiquitous",
      "phonetic": "/juːˈbɪkwɪtəs/",
      "pos": "adj",
      "definition_en": "Present everywhere at the same time",
      "meaning_vi": "Có mặt ở khắp nơi, phổ biến",
      "examples": [
        { "en": "Smartphones have become ubiquitous.", "vi": "Điện thoại thông minh đã trở nên phổ biến khắp nơi." },
        { "en": "Coffee shops are ubiquitous in this city.", "vi": "Quán cà phê có mặt khắp nơi trong thành phố này." }
      ],
      "synonyms": ["omnipresent", "pervasive", "universal"],
      "origin": "From Latin 'ubique' meaning everywhere",
      "categoryId": "beautiful_words",
      "level": "advanced"
    },
    {
      "id": "w14",
      "term": "ephemeral",
      "phonetic": "/ɪˈfemərəl/",
      "pos": "adj",
      "definition_en": "Lasting for a very short time",
      "meaning_vi": "Ngắn ngủi, phù du",
      "examples": [
        { "en": "Fame can be ephemeral.", "vi": "Danh tiếng có thể rất phù du." },
        { "en": "The beauty of cherry blossoms is ephemeral.", "vi": "Vẻ đẹp của hoa anh đào thật ngắn ngủi." }
      ],
      "synonyms": ["fleeting", "transient", "momentary", "brief"],
      "origin": "From Greek 'ephemeros' meaning lasting only a day",
      "categoryId": "beautiful_words",
      "level": "advanced"
    },
    {
      "id": "w15",
      "term": "algorithm",
      "phonetic": "/ˈælɡərɪðəm/",
      "pos": "noun",
      "definition_en": "A set of rules for solving a problem",
      "meaning_vi": "Thuật toán",
      "examples": [
        { "en": "The algorithm sorts data efficiently.", "vi": "Thuật toán sắp xếp dữ liệu một cách hiệu quả." },
        { "en": "Social media algorithms determine what you see.", "vi": "Thuật toán mạng xã hội quyết định những gì bạn thấy." }
      ],
      "synonyms": ["procedure", "formula", "method"],
      "categoryId": "technology",
      "level": "intermediate"
    },
    {
      "id": "w16",
      "term": "sustainable",
      "phonetic": "/səˈsteɪnəbl/",
      "pos": "adj",
      "definition_en": "Able to be maintained over time without harming the environment",
      "meaning_vi": "Bền vững",
      "examples": [
        { "en": "We need sustainable energy sources.", "vi": "Chúng ta cần nguồn năng lượng bền vững." },
        { "en": "Sustainable living is important.", "vi": "Lối sống bền vững rất quan trọng." }
      ],
      "synonyms": ["eco-friendly", "renewable", "green"],
      "categoryId": "environment",
      "level": "intermediate"
    },
    {
      "id": "w17",
      "term": "entrepreneur",
      "phonetic": "/ˌɒntrəprəˈnɜːr/",
      "pos": "noun",
      "definition_en": "A person who starts and runs their own business",
      "meaning_vi": "Doanh nhân, người khởi nghiệp",
      "examples": [
        { "en": "She became a successful entrepreneur.", "vi": "Cô ấy đã trở thành một doanh nhân thành công." },
        { "en": "Entrepreneurs take calculated risks.", "vi": "Doanh nhân chấp nhận rủi ro có tính toán." }
      ],
      "synonyms": ["businessperson", "founder", "tycoon"],
      "origin": "From French 'entreprendre' meaning to undertake",
      "categoryId": "business",
      "level": "intermediate"
    },
    {
      "id": "w18",
      "term": "litigation",
      "phonetic": "/ˌlɪtɪˈɡeɪʃn/",
      "pos": "noun",
      "definition_en": "The process of taking legal action",
      "meaning_vi": "Tranh tụng, kiện tụng",
      "examples": [
        { "en": "The litigation lasted for years.", "vi": "Vụ kiện tụng kéo dài nhiều năm." },
        { "en": "They want to avoid costly litigation.", "vi": "Họ muốn tránh kiện tụng tốn kém." }
      ],
      "synonyms": ["lawsuit", "legal action", "court case"],
      "categoryId": "legal_terms",
      "level": "advanced"
    },
    {
      "id": "w19",
      "term": "break a leg",
      "phonetic": "/breɪk ə leɡ/",
      "pos": "noun",
      "definition_en": "A way to wish someone good luck, especially before a performance",
      "meaning_vi": "Chúc may mắn (thường dùng trong biểu diễn)",
      "examples": [
        { "en": "Break a leg at your audition!", "vi": "Chúc may mắn trong buổi thử vai!" },
        { "en": "She told him to break a leg before the show.", "vi": "Cô ấy chúc anh ta may mắn trước buổi diễn." }
      ],
      "synonyms": ["good luck", "best wishes"],
      "categoryId": "expressions",
      "level": "beginner"
    },
    {
      "id": "w20",
      "term": "ghosting",
      "phonetic": "/ˈɡoʊstɪŋ/",
      "pos": "noun",
      "definition_en": "The practice of suddenly cutting off all contact with someone",
      "meaning_vi": "Biến mất không lời từ biệt, ngắt liên lạc đột ngột",
      "examples": [
        { "en": "Ghosting has become common in dating.", "vi": "Việc biến mất không lời từ biệt đã trở nên phổ biến trong hẹn hò." },
        { "en": "She was hurt by his ghosting.", "vi": "Cô ấy bị tổn thương khi anh ta đột ngột ngắt liên lạc." }
      ],
      "synonyms": ["disappearing", "ignoring"],
      "categoryId": "slang",
      "level": "beginner"
    }
  ]
}
